onc_hydrophone_data/__init__.py
onc_hydrophone_data/audio/__init__.py
onc_hydrophone_data/audio/audio_utils.py
onc_hydrophone_data/audio/spectrogram_generator.py
onc_hydrophone_data/data/__init__.py
onc_hydrophone_data/data/config_utils.py
onc_hydrophone_data/data/deployment_checker.py
onc_hydrophone_data/data/hydrophone_downloader.py
onc_hydrophone_data/data/location_mappings.py
onc_hydrophone_data/data/onc_requests.py
onc_hydrophone_data/data/segment.py
onc_hydrophone_data/data/trim_image.py
onc_hydrophone_data/data/downloader/__init__.py
onc_hydrophone_data/data/downloader/audio_backends.py
onc_hydrophone_data/data/downloader/audio_workflows.py
onc_hydrophone_data/data/downloader/clip_io.py
onc_hydrophone_data/data/downloader/constants.py
onc_hydrophone_data/data/downloader/core.py
onc_hydrophone_data/data/downloader/custom_spectrograms.py
onc_hydrophone_data/data/downloader/deployment_workflows.py
onc_hydrophone_data/data/downloader/directories.py
onc_hydrophone_data/data/downloader/flags.py
onc_hydrophone_data/data/downloader/models.py
onc_hydrophone_data/data/downloader/onc_downloads.py
onc_hydrophone_data/data/downloader/parallel_requests.py
onc_hydrophone_data/data/downloader/request_execution.py
onc_hydrophone_data/data/downloader/request_parsing.py
onc_hydrophone_data/data/downloader/sampling_workflows.py
onc_hydrophone_data/data/downloader/spectrogram_workflows.py
onc_hydrophone_data/data/downloader/time_utils.py
onc_hydrophone_data/data/downloader/validation.py
onc_hydrophone_data/onc/__init__.py
onc_hydrophone_data/onc/common.py
onc_hydrophone_data/utils/__init__.py
onc_hydrophone_data/utils/download_helpers.py
onc_hydrophone_data/utils/plotting.py
onc_hydrophone_data-0.2.2.dist-info/METADATA
onc_hydrophone_data-0.2.2.dist-info/WHEEL
onc_hydrophone_data-0.2.2.dist-info/top_level.txt
onc_hydrophone_data-0.2.2.dist-info/RECORD
