Metadata-Version: 2.4
Name: onc-hydrophone-data
Version: 0.2.2
Summary: Tools for downloading and processing Ocean Networks Canada hydrophone data
Author-email: Spencer Bialek <sbialek@uvic.ca>
License: MIT
Project-URL: Homepage, https://github.com/Spiffical/onc-hydrophone-data
Project-URL: Repository, https://github.com/Spiffical/onc-hydrophone-data
Requires-Python: >=3.9
Requires-Dist: onc>=2.3.0
Requires-Dist: numpy>=1.20.0
Requires-Dist: scipy>=1.7.3
Requires-Dist: matplotlib>=3.7.0
Requires-Dist: pillow>=9.0.0
Requires-Dist: requests>=2.28.0
Requires-Dist: torch>=2.0.0
Requires-Dist: torchaudio>=2.0.0
Requires-Dist: torchcodec>=0.2.0
Requires-Dist: python-dotenv>=1.0.0
Requires-Dist: tqdm>=4.65.0
Requires-Dist: soundfile>=0.12.0
Requires-Dist: librosa>=0.10.0
Requires-Dist: PyYAML>=6.0
Requires-Dist: plotly>=5.18.0
Requires-Dist: ipywidgets>=8.1.0
Requires-Dist: pandas>=2.1.0
Requires-Dist: anywidget>=0.9.0
